Workbook

Sheet daftar saldo awal
A1: No Akun | B1: Nama Akun | C1: Side | D1: Amount
A2: 1-1100 | B2: Kas | C2: Debit | D2: 100000000
A3: 1-1200 | B3: Piutang usaha | C3: Debit | D3: 8640000
A4: 1-1300 | B4: Persediaan barang dagang | C4: Debit | D4: 34390000
A5: 1-1310 | B5: Persediaan stok madu gudang | C5: Debit | D5: 563470001
A6: 1-1400 | B6: Perlengkapan toko | C6: Debit | D6: 41000000
A7: 1-1500 | B7: Tanah | C7: Debit | D7: 3600000000
A8: 1-1510 | B8: Bangunan | C8: Debit | D8: 150000000
A9: 1-1511 | B9: Akumulasi penyusutan bangunan | C9: Kredit | E9: 36000000
A10: 1-1600 | B10: Kendaraan | C10: Debit | D10: 250000000
A11: 1-1610 | B11: Akumulasi penyusutan kendaraan | C11: Kredit | E11: 1.0833333e+08
A12: 1-1700 | B12: Peralatan | C12: Debit | D12: 80000000
A13: 1-1710 | B13: Akumulasi penyusutan peralatan | C13: Kredit | E13: 48000000
A14: 2-2100 | B14: Hutang dagang | C14: Kredit | E14: 17340000
A15: 3-3000 | B15: Modal | C15: Kredit | E15: 4.5733433e+09
A16: 4-4000 | B16: Penjualan barang dagang | C16: Kredit | E16: 185000000
A17: 4-4100 | B17: Retur penjualan | C17: Debit | D17: 2700000
A18: 5-5000 | B18: Harga pokok penjualan | C18: Debit | D18: 34390000
A19: 6-6100 | B19: Beban telepon, air, dan listrik | C19: Debit | D19: 300000
A20: 6-6200 | B20: Beban perlengkapan | C20: Debit | D20: 11460000
A21: 6-6300 | B21: Beban pemeliharaan | C21: Debit | D21: 6000000
A22: 6-6400 | B22: Beban gaji produksi | C22: Debit | D22: 14000000
A23: 6-6500 | B23: Beban gaji pemeliharaan lebah | C23: Debit | D23: 1000000
A24: 6-6600 | B24: Beban transportasi pemeliharaan lebah | C24: Debit | D24: 5000000
A25: 6-6700 | B25: Beban transportasi penjualan lebah | C25: Debit | D25: 2000000
A26: 6-6800 | B26: Beban depresiasi aktiva tetap | C26: Debit | D26: 63666667
D27: =SUM(D2:D26) -> 4.9680167e+09 | E27: =SUM(E2:E26) -> 4.9680167e+09

Sheet laba rugi
A1: PENJUALAN
A2: Penjualan Barang Dagang | B2: ='daftar saldo awal'!E16 -> 185000000
A3: Retur Penjualan | B3: ='daftar saldo awal'!D17 -> 2700000
A4: Penjualan Bersih | C4: =B2-B3 -> 182300000
A6: Harga Pokok Penjualan | C6: ='daftar saldo awal'!D18 -> 34390000
A7: LABA KOTOR | C7: =C4-C6 -> 147910000
A9: BEBAN OPERASIONAL
A10: Beban telepon, air, dan listrik | B10: 300000
A11: Beban perlengkapan | B11: 11460000
A12: Beban pemeliharaan | B12: 6000000
A13: Beban gaji produksi | B13: 14000000
A14: Beban gaji pemeliharaan lebah | B14: 1000000
A15: Beban transportasi pemeliharaan lebah | B15: 5000000
A16: Beban transportasi penjualan lebah | B16: 2000000
A17: Beban depresiasi aktiva tetap | B17: 63666667
A18: Total Beban Operasional | C18: =SUM(B10:B17) -> 1.0342667e+08
A19: LABA BERSIH | C19: =C7-C18 -> 44483333

Sheet perubahan ekuitas
A1: KETERANGAN
A2: Saldo Modal Awal | B2: ='daftar saldo awal'!E15 -> 4.5733433e+09
A3: Laba Bersih | B3: ='laba rugi'!C19 -> 44483333
A4: Saldo Modal Akhir | B4: =B2+B3 -> 4.6178267e+09

Sheet posisi keuangan
A1: AKTIVA
A2: ASET LANCAR
A3: Kas | B3: ='daftar saldo awal'!D2 -> 100000000
A4: Piutang usaha | B4: ='daftar saldo awal'!D3 -> 8640000
A5: Persediaan barang dagang | B5: ='daftar saldo awal'!D4 -> 34390000
A6: Persediaan stok madu gudang | B6: ='daftar saldo awal'!D5 -> 563470001
A7: Perlengkapan toko | B7: ='daftar saldo awal'!D6 -> 41000000
A8: Total Aset Lancar | C8: =SUM(B3:B7) -> 747500001
A10: ASET TETAP
A11: Tanah | B11: ='daftar saldo awal'!D7 -> 3600000000
A12: Bangunan | B12: ='daftar saldo awal'!D8 -> 150000000
A13: Akumulasi penyusutan bangunan | B13: =-'daftar saldo awal'!E9 -> -36000000
A14: Kendaraan | B14: ='daftar saldo awal'!D10 -> 250000000
A15: Akumulasi penyusutan kendaraan | B15: =-'daftar saldo awal'!E11 -> -1.0833333e+08
A16: Peralatan | B16: ='daftar saldo awal'!D12 -> 80000000
A17: Akumulasi penyusutan peralatan | B17: =-'daftar saldo awal'!E13 -> -48000000
A18: Total Aset Tetap | C18: =SUM(B11:B17) -> 3.8876667e+09
A19: TOTAL ASET | C19: =C8+C18 -> 4.6351667e+09
A21: KEWAJIBAN DAN EKUITAS
A22: KEWAJIBAN
A23: Hutang Dagang | B23: ='daftar saldo awal'!E14 -> 17340000
A24: Total Kewajiban | C24: =SUM(B23) -> 17340000
A26: EKUITAS
A27: Modal Awal | B27: ='daftar saldo awal'!E15 -> 4.5733433e+09
A28: Laba Bersih | B28: ='laba rugi'!C19 -> 44483333
A29: Total Ekuitas | C29: =SUM(B27:B28) -> 4.6178267e+09
A31: TOTAL KEWAJIBAN DAN EKUITAS | C31: =C29+C24 -> 4.6351667e+09

Sheet Depreciation Detail
A1: Asset | B1: Cost (Rp) | C1: Useful life (years) | D1: Current period depreciation (Rp)
A2: Bangunan | B2: 150000000 | C2: 25 | D2: 6000000
A3: Kendaraan | B3: 250000000 | C3: 6 | D3: 41666667
A4: Peralatan | B4: 80000000 | C4: 5 | D4: 16000000
A5: Total (current period) | D5: 63666667
